quantum_decomp/__init__.py
quantum_decomp/qsharp_integration_test.py
quantum_decomp/quantum_decomp_main.py
quantum_decomp/quantum_decomp_test.py
quantum_decomp/src/__init__.py
quantum_decomp/src/decompose_2x2.py
quantum_decomp/src/decompose_2x2_test.py
quantum_decomp/src/decompose_4x4.py
quantum_decomp/src/decompose_4x4_test.py
quantum_decomp/src/gate.py
quantum_decomp/src/gate2.py
quantum_decomp/src/gate2_test.py
quantum_decomp/src/gate_test.py
quantum_decomp/src/linalg.py
quantum_decomp/src/test_utils.py
quantum_decomp/src/two_level_unitary.py
quantum_decomp/src/utils.py
quantum_decomp-1.1.2.dist-info/LICENSE
quantum_decomp-1.1.2.dist-info/METADATA
quantum_decomp-1.1.2.dist-info/WHEEL
quantum_decomp-1.1.2.dist-info/top_level.txt
quantum_decomp-1.1.2.dist-info/RECORD
