Metadata-Version: 2.2
Name: quantum_decomp
Version: 1.1.2
Summary: Tool for decomposing unitary matrix into quantum gates
Home-page: https://github.com/fedimser/quantum_decomp
Author: Dmytro Fedoriaka
License: MIT
Requires-Python: >=3.7
License-File: LICENSE
Requires-Dist: numpy>=1.17
Dynamic: author
Dynamic: description
Dynamic: description-content-type
Dynamic: home-page
Dynamic: license
Dynamic: requires-dist
Dynamic: requires-python
Dynamic: summary
